seatlock/__init__.py
seatlock/manager.py
seatlock/seat.py
seatlock/states.py
seatlock-0.1.0.dist-info/licenses/License
seatlock-0.1.0.dist-info/METADATA
seatlock-0.1.0.dist-info/WHEEL
seatlock-0.1.0.dist-info/top_level.txt
seatlock-0.1.0.dist-info/RECORD
