Metadata-Version: 2.4
Name: seatlock
Version: 0.1.0
Summary: A concurrency-safe seat allocation and booking engine
Author: Aditya
License: MIT
Classifier: Programming Language :: Python :: 3
Classifier: Programming Language :: Python :: 3 :: Only
Classifier: Operating System :: OS Independent
Classifier: License :: OSI Approved :: MIT License
Classifier: Intended Audience :: Developers
Classifier: Topic :: Software Development :: Libraries
Requires-Python: >=3.8
License-File: License
Dynamic: license-file
